playfilm_shared/__init__.py
playfilm_shared/decorators.py
playfilm_shared/exceptions.py
playfilm_shared-2.0.1.dist-info/LICENSE
playfilm_shared-2.0.1.dist-info/METADATA
playfilm_shared-2.0.1.dist-info/WHEEL
playfilm_shared-2.0.1.dist-info/top_level.txt
playfilm_shared-2.0.1.dist-info/RECORD
