Metadata-Version: 2.1
Name: playfilm-shared
Version: 2.0.1
Summary: Shared components package
Author-email: Vic Escribano <victor@playfilm.tv>, Pau Juanes <pau@playfilm.tv>, Richard Sudario <richard@playfilm.tv>, Jaume Serra <jaume@playfilm.tv>
Project-URL: Homepage, https://bitbucket.org/playfilm/playfilm-shared/src/main/
Classifier: Programming Language :: Python :: 3
Classifier: License :: OSI Approved :: MIT License
Classifier: Operating System :: OS Independent
Requires-Python: >=3.9
License-File: LICENSE
